MANIFEST.in
NEWS.txt
README.rst
setup.py
src/updatedir/__init__.py
src/updatedir.egg-info/PKG-INFO
src/updatedir.egg-info/SOURCES.txt
src/updatedir.egg-info/dependency_links.txt
src/updatedir.egg-info/entry_points.txt
src/updatedir.egg-info/not-zip-safe
src/updatedir.egg-info/requires.txt
src/updatedir.egg-info/top_level.txt