Metadata-Version: 1.0
Name: updatedir
Version: 0.1.2
Summary: Rsync-like directory updating over multiple protocols
Home-page: http://github.com/saffsd/updatedir
Author: Marco Lui
Author-email: saffsd@gmail.com
License: GPL
Platform: UNKNOWN
